{"title":"WWE NXT 2015 10 06 Respect Preview 720p WEBRip h264-WD -={SPARRO","uid":12529748,"size":1948060024,"categoryP":"video","categoryS":"hd___tv_shows","magnet":"?xt=urn:btih:15d2c6c77026409301ceabe120e58ac1bb9d6cf2&amp;dn=WWE+NXT+2015+10+06+Respect+Preview+720p+WEBRip+h264-WD+-%3D%7BSPARRO&amp;tr=udp%3A%2F%2Ftracker.leechers-paradise.org%3A6969&amp;tr=udp%3A%2F%2Fzer0day.ch%3A1337&amp;tr=udp%3A%2F%2Fopen.demonii.com%3A1337&amp;tr=udp%3A%2F%2Ftracker.coppersurfer.tk%3A6969&amp;tr=udp%3A%2F%2Fexodus.desync.com%3A6969","seeders":0,"leechers":0,"uploader":"CenaCme","files":2,"time":1444221073,"description":"Pre-Air\r\n\r\nJoin Corey Graves for this in-depth preview of NXT TakeOver: Respect!\r\n\r\nEvent: WWE.NXT.2015.10.06.Respect.Preview.720p.WEBRip.h264-WD\r\nReleased: 2015.10.05\r\nSource: WWE Network\r\nResolution: 1280 x 720 @ 29.970 FPS\r\nVideo: H.264 @ 4500 kbps\r\nAudio: AAC @ 96 kbps\r\nSize: 1.81 GB\r\nRuntime: 58mn 32sec\r\n\r\nWD: The Original\r\nHEEL\r\n\r\nUntouched/remuxed video stream from the WWE Network.\r\n\r\n\r\nScreens:\r\n \nhttp://imgsparrow.co/image/80m","torrent":{"xt":"urn:btih:15d2c6c77026409301ceabe120e58ac1bb9d6cf2","amp;dn":"WWE+NXT+2015+10+06+Respect+Preview+720p+WEBRip+h264-WD+-%3D%7BSPARRO","amp;tr":["udp%3A%2F%2Ftracker.leechers-paradise.org%3A6969","udp%3A%2F%2Fzer0day.ch%3A1337","udp%3A%2F%2Fopen.demonii.com%3A1337","udp%3A%2F%2Ftracker.coppersurfer.tk%3A6969","udp%3A%2F%2Fexodus.desync.com%3A6969"],"infoHash":"15d2c6c77026409301ceabe120e58ac1bb9d6cf2","infoHashBuffer":{"type":"Buffer","data":[21,210,198,199,112,38,64,147,1,206,171,225,32,229,138,193,187,157,108,242]},"announce":[],"urlList":[]}}