{"title":"Eastenders.2015.10.12.WEBRip.x264-SOAPBOX","uid":12564474,"size":193286581,"categoryP":"video","categoryS":"tv_shows","magnet":"?xt=urn:btih:15fb836aa15b20f5c6f6580a5ae9842b715b4ea8&amp;dn=Eastenders.2015.10.12.WEBRip.x264-SOAPBOX&amp;tr=udp%3A%2F%2Ftracker.leechers-paradise.org%3A6969&amp;tr=udp%3A%2F%2Fzer0day.ch%3A1337&amp;tr=udp%3A%2F%2Fopen.demonii.com%3A1337&amp;tr=udp%3A%2F%2Ftracker.coppersurfer.tk%3A6969&amp;tr=udp%3A%2F%2Fexodus.desync.com%3A6969","seeders":0,"leechers":0,"uploader":"TvTeam","files":5,"time":1444762228,"description":"------------------------------------------------------------------------\r\n\r  https://www.torrenting.com\r\n\r\nSign up is OPEN - for time being. Come and have fun.\r\n\r\nGeneral\r\nFilename.......: eastenders.2015.10.12.webrip.x264-soapbox\r\nContainer......: MPEG-4\r\nDuration.......: 28mn 31s 40ms\r\nSize...........: 179 MiB\r\n\r\nVideo\r\nCodec..........: AVC\r\nResolution.....: 720x404\r\nAspect ratio...: 1.782\r\nBit rate.......: 779 Kbps\r\nFrame rate.....: 25.000 fps\r\n\r\nAudio\r\nFormat.........: AAC LC \r\nChannels.......: 2 channels\r\nBit rate.......: 93.5 Kbps\r\nLanguage.......: English\r\n \r\n\r\nGenre...............: Drama\r\n\r\nLink...............: http://www.tvmaze.com/shows/793/eastenders\r\n\r\nNews...............: Looking for good/secure Gbit+sites to affiliate\r\nContact............: FiND US","torrent":{"xt":"urn:btih:15fb836aa15b20f5c6f6580a5ae9842b715b4ea8","amp;dn":"Eastenders.2015.10.12.WEBRip.x264-SOAPBOX","amp;tr":["udp%3A%2F%2Ftracker.leechers-paradise.org%3A6969","udp%3A%2F%2Fzer0day.ch%3A1337","udp%3A%2F%2Fopen.demonii.com%3A1337","udp%3A%2F%2Ftracker.coppersurfer.tk%3A6969","udp%3A%2F%2Fexodus.desync.com%3A6969"],"infoHash":"15fb836aa15b20f5c6f6580a5ae9842b715b4ea8","infoHashBuffer":{"type":"Buffer","data":[21,251,131,106,161,91,32,245,198,246,88,10,90,233,132,43,113,91,78,168]},"announce":[],"urlList":[]}}