{"title":"EroticaX.15.09.25.Jezabel.Vessir.Staying.In.XXX.1080p.MP4.KTR","uid":12496318,"size":1295658794,"categoryP":"porn","categoryS":"movie_clips","magnet":"?xt=urn:btih:17a03c6fbb12608d132a299e64402b53663c796d&amp;dn=EroticaX.15.09.25.Jezabel.Vessir.Staying.In.XXX.1080p.MP4.KTR&amp;tr=udp%3A%2F%2Ftracker.leechers-paradise.org%3A6969&amp;tr=udp%3A%2F%2Fzer0day.ch%3A1337&amp;tr=udp%3A%2F%2Fopen.demonii.com%3A1337&amp;tr=udp%3A%2F%2Ftracker.coppersurfer.tk%3A6969&amp;tr=udp%3A%2F%2Fexodus.desync.com%3A6969","seeders":0,"leechers":0,"uploader":"Piratepr0n","files":1,"time":1443272022,"description":"-------------------------------------------------------------------------------------\nName:\nEroticaX.15.09.25.Jezabel.Vessir.Staying.In.XXX.1080p.MP4.KTR\n-------------------------------------------------------------------------------------\nFile list:\neroticax.15.09.25.jezabel.vessir.staying.in.mp4 (1.21 GiB | 1920x1080 | 24min 43s | MPEG-4) \nhttp://imgfapper.com/img-56067a3764b82.html","torrent":{"xt":"urn:btih:17a03c6fbb12608d132a299e64402b53663c796d","amp;dn":"EroticaX.15.09.25.Jezabel.Vessir.Staying.In.XXX.1080p.MP4.KTR","amp;tr":["udp%3A%2F%2Ftracker.leechers-paradise.org%3A6969","udp%3A%2F%2Fzer0day.ch%3A1337","udp%3A%2F%2Fopen.demonii.com%3A1337","udp%3A%2F%2Ftracker.coppersurfer.tk%3A6969","udp%3A%2F%2Fexodus.desync.com%3A6969"],"infoHash":"17a03c6fbb12608d132a299e64402b53663c796d","infoHashBuffer":{"type":"Buffer","data":[23,160,60,111,187,18,96,141,19,42,41,158,100,64,43,83,102,60,121,109]},"announce":[],"urlList":[]}}