{"title":"Shemale-Club - Carla Novais, Rayane Lenox, Kamper [.mp4]","uid":12571227,"size":949599513,"categoryP":"porn","categoryS":"hd___movies","magnet":"?xt=urn:btih:1b08c6d418f72eede37948c6f1c57ecf322dc0ce&amp;dn=Shemale-Club+-+Carla+Novais%2C+Rayane+Lenox%2C+Kamper+%5B.mp4%5D&amp;tr=udp%3A%2F%2Ftracker.leechers-paradise.org%3A6969&amp;tr=udp%3A%2F%2Fzer0day.ch%3A1337&amp;tr=udp%3A%2F%2Fopen.demonii.com%3A1337&amp;tr=udp%3A%2F%2Ftracker.coppersurfer.tk%3A6969&amp;tr=udp%3A%2F%2Fexodus.desync.com%3A6969","seeders":0,"leechers":1,"uploader":"C47wh15p3r3r","files":3,"time":1444851856,"description":"Shemale-Club - Carla Novais, Rayane Lenox, Kamper [.mp4]\r\n\r\nScreenshots: \nhttp://imgarte.com/?v=439082 \nhttp://imgarte.com/?v=243298","torrent":{"xt":"urn:btih:1b08c6d418f72eede37948c6f1c57ecf322dc0ce","amp;dn":"Shemale-Club+-+Carla+Novais%2C+Rayane+Lenox%2C+Kamper+%5B.mp4%5D","amp;tr":["udp%3A%2F%2Ftracker.leechers-paradise.org%3A6969","udp%3A%2F%2Fzer0day.ch%3A1337","udp%3A%2F%2Fopen.demonii.com%3A1337","udp%3A%2F%2Ftracker.coppersurfer.tk%3A6969","udp%3A%2F%2Fexodus.desync.com%3A6969"],"infoHash":"1b08c6d418f72eede37948c6f1c57ecf322dc0ce","infoHashBuffer":{"type":"Buffer","data":[27,8,198,212,24,247,46,237,227,121,72,198,241,197,126,207,50,45,192,206]},"announce":[],"urlList":[]}}