{"title":"PornMegaLoad.15.10.08.Layla.Lamora.Gives.A.Hummer.XXX.1080p.MP4-","uid":12619893,"size":1261359636,"categoryP":"porn","categoryS":"hd___movies","magnet":"?xt=urn:btih:225c7a56ce979faa0e08ee9e25b0fef9dd1a5218&amp;dn=PornMegaLoad.15.10.08.Layla.Lamora.Gives.A.Hummer.XXX.1080p.MP4-&amp;tr=udp%3A%2F%2Ftracker.leechers-paradise.org%3A6969&amp;tr=udp%3A%2F%2Fzer0day.ch%3A1337&amp;tr=udp%3A%2F%2Fopen.demonii.com%3A1337&amp;tr=udp%3A%2F%2Ftracker.coppersurfer.tk%3A6969&amp;tr=udp%3A%2F%2Fexodus.desync.com%3A6969","seeders":0,"leechers":1,"uploader":"0-DayXXX","files":1,"time":1445580702,"description":"---------------------------------------\nPornMegaLoad.15.10.08.Layla.Lamora.Gives.A.Hummer.XXX.1080p.MP4-KTR\n---------------------------------------\nScreenshot(s): \nhttp://imgsay.com/?v=885891.jpg\n\n---------------------------------------\nFormat:\t\tMPEG-4\nSize:\t\t1.17 GiB\nDuration:\t20min 45s\nResolution:\t1920x1080\nBitrate:\t8000Kbps\n---------------------------------------\nIf you like this torrent, please post a comment!\n\nDon't forget to seed!","torrent":{"xt":"urn:btih:225c7a56ce979faa0e08ee9e25b0fef9dd1a5218","amp;dn":"PornMegaLoad.15.10.08.Layla.Lamora.Gives.A.Hummer.XXX.1080p.MP4-","amp;tr":["udp%3A%2F%2Ftracker.leechers-paradise.org%3A6969","udp%3A%2F%2Fzer0day.ch%3A1337","udp%3A%2F%2Fopen.demonii.com%3A1337","udp%3A%2F%2Ftracker.coppersurfer.tk%3A6969","udp%3A%2F%2Fexodus.desync.com%3A6969"],"infoHash":"225c7a56ce979faa0e08ee9e25b0fef9dd1a5218","infoHashBuffer":{"type":"Buffer","data":[34,92,122,86,206,151,159,170,14,8,238,158,37,176,254,249,221,26,82,24]},"announce":[],"urlList":[]}}