{"title":"[BlackShemaleHardcore] Anna After Dark Fucks JC! (22 Oct 2015)","uid":12618208,"size":200546128,"categoryP":"porn","categoryS":"movie_clips","magnet":"?xt=urn:btih:297b6d9f5b5c3ddf148b7b7bae022d262147455d&amp;dn=%5BBlackShemaleHardcore%5D+Anna+After+Dark+Fucks+JC%21+%2822+Oct+2015%29&amp;tr=udp%3A%2F%2Ftracker.leechers-paradise.org%3A6969&amp;tr=udp%3A%2F%2Fzer0day.ch%3A1337&amp;tr=udp%3A%2F%2Fopen.demonii.com%3A1337&amp;tr=udp%3A%2F%2Ftracker.coppersurfer.tk%3A6969&amp;tr=udp%3A%2F%2Fexodus.desync.com%3A6969","seeders":0,"leechers":1,"uploader":"KayWily","files":1,"time":1445552156,"description":"[BlackShemaleHardcore] Anna After Dark Fucks JC! (22 Oct 2015)\r\n\r\n \nhttp://porn-harbor.com/image/Ma","torrent":{"xt":"urn:btih:297b6d9f5b5c3ddf148b7b7bae022d262147455d","amp;dn":"%5BBlackShemaleHardcore%5D+Anna+After+Dark+Fucks+JC%21+%2822+Oct+2015%29","amp;tr":["udp%3A%2F%2Ftracker.leechers-paradise.org%3A6969","udp%3A%2F%2Fzer0day.ch%3A1337","udp%3A%2F%2Fopen.demonii.com%3A1337","udp%3A%2F%2Ftracker.coppersurfer.tk%3A6969","udp%3A%2F%2Fexodus.desync.com%3A6969"],"infoHash":"297b6d9f5b5c3ddf148b7b7bae022d262147455d","infoHashBuffer":{"type":"Buffer","data":[41,123,109,159,91,92,61,223,20,139,123,123,174,2,45,38,33,71,69,93]},"announce":[],"urlList":[]}}