{"title":"Las Vegas TV Show Season 1","uid":5292674,"size":8443641856,"categoryP":"video","categoryS":"tv_shows","magnet":"?xt=urn:btih:326101ba155e52ca4deb0ac2dd10b248f6600930&amp;dn=Las+Vegas+TV+Show+Season+1&amp;tr=udp%3A%2F%2Ftracker.openbittorrent.com%3A80&amp;tr=udp%3A%2F%2Fopen.demonii.com%3A1337&amp;tr=udp%3A%2F%2Ftracker.coppersurfer.tk%3A6969&amp;tr=udp%3A%2F%2Fexodus.desync.com%3A6969","seeders":0,"leechers":3,"uploader":"hascal","files":23,"time":1263946398,"description":"Season 1 of Las Vegas in english.\n\nEnjoy","torrent":{"xt":"urn:btih:326101ba155e52ca4deb0ac2dd10b248f6600930","amp;dn":"Las+Vegas+TV+Show+Season+1","amp;tr":["udp%3A%2F%2Ftracker.openbittorrent.com%3A80","udp%3A%2F%2Fopen.demonii.com%3A1337","udp%3A%2F%2Ftracker.coppersurfer.tk%3A6969","udp%3A%2F%2Fexodus.desync.com%3A6969"],"infoHash":"326101ba155e52ca4deb0ac2dd10b248f6600930","infoHashBuffer":{"type":"Buffer","data":[50,97,1,186,21,94,82,202,77,235,10,194,221,16,178,72,246,96,9,48]},"announce":[],"urlList":[]}}