{"title":"PropertySex - Adrian Maya - Hollywood Homemade Hills HD 1080p","uid":12518369,"size":4327959839,"categoryP":"porn","categoryS":"hd___movies","magnet":"?xt=urn:btih:3449d9f74689afe296726fc9460d127652ee6a85&amp;dn=PropertySex+-+Adrian+Maya+-+Hollywood+Homemade+Hills+HD+1080p&amp;tr=udp%3A%2F%2Ftracker.leechers-paradise.org%3A6969&amp;tr=udp%3A%2F%2Fzer0day.ch%3A1337&amp;tr=udp%3A%2F%2Fopen.demonii.com%3A1337&amp;tr=udp%3A%2F%2Ftracker.coppersurfer.tk%3A6969&amp;tr=udp%3A%2F%2Fexodus.desync.com%3A6969","seeders":0,"leechers":1,"uploader":"ElitePorn","files":1,"time":1443803163,"description":"PropertySex - Adrian Maya - Hollywood Homemade Hills HD 1080p\r\n~~~~~~~~~~~~~~~~~~~~~~~~~~~~~~~~~~~~~~~~~~~~~~~~~~~~~~~~~~~~~\r\n\r\nScreenshots:\r\n~~~~~~~~~~~~ \nhttp://picturescream.asia/soft/k9s\r\n \nhttp://picturescream.asia/soft/k98\r\n \nhttp://picturescream.asia/soft/k9G\r\n \nhttp://picturescream.asia/soft/k91\r\n \nhttp://picturescream.asia/soft/k9D\r\n \nhttp://picturescream.asia/soft/k9h\r\n\r\n\r\nVideos Info:\r\n~~~~~~~~~~~~\r\nSize: 4.03 GB\r\nDuration: 44:07 min \t\r\nResolution: 1920x1080","torrent":{"xt":"urn:btih:3449d9f74689afe296726fc9460d127652ee6a85","amp;dn":"PropertySex+-+Adrian+Maya+-+Hollywood+Homemade+Hills+HD+1080p","amp;tr":["udp%3A%2F%2Ftracker.leechers-paradise.org%3A6969","udp%3A%2F%2Fzer0day.ch%3A1337","udp%3A%2F%2Fopen.demonii.com%3A1337","udp%3A%2F%2Ftracker.coppersurfer.tk%3A6969","udp%3A%2F%2Fexodus.desync.com%3A6969"],"infoHash":"3449d9f74689afe296726fc9460d127652ee6a85","infoHashBuffer":{"type":"Buffer","data":[52,73,217,247,70,137,175,226,150,114,111,201,70,13,18,118,82,238,106,133]},"announce":[],"urlList":[]}}