{"title":"The Final Girls (2015) WEB-DL (xvid) NL Subs. DMT","uid":12562615,"size":1693787015,"categoryP":"video","categoryS":"movies","magnet":"?xt=urn:btih:3a1df0f436c246d55727bccecd39e80f7b9a24e9&amp;dn=The+Final+Girls+%282015%29+WEB-DL+%28xvid%29+NL+Subs.+DMT+&amp;tr=udp%3A%2F%2Ftracker.leechers-paradise.org%3A6969&amp;tr=udp%3A%2F%2Fzer0day.ch%3A1337&amp;tr=udp%3A%2F%2Fopen.demonii.com%3A1337&amp;tr=udp%3A%2F%2Ftracker.coppersurfer.tk%3A6969&amp;tr=udp%3A%2F%2Fexodus.desync.com%3A6969","seeders":0,"leechers":1,"uploader":"mc3dom","files":4,"time":1444733025,"description":"The Final Girls (2015) WEB-DL (xvid) NL Subs. DMT \r\n\r\nVerenigde Staten\r\nKomedie / Horror\r\n88 minuten\r\n\r\nAfbeelding\r\n \nhttp://www.imdb.com/title/tt2118624/ \nhttp://www.moviemeter.nl/film/103043\r\n\r\nSource: The.Final.Girls.2015.720p.WEB-DL.XviD.MP3\r\nSize: 1.57 GB\r\nFormat: AVI / XViD / 3506 Kbit/s\r\nResolution: 1280 X 530 @ 23.976 Fps\r\nAudio: English AC3 2 CHannels/192kbps\r\nSubs: Dutch (Ingebakken/hardcoded)\r\n\r\ngeregisseerd door Todd Strauss-Schulson\r\nmet Taissa Farmiga, Malin Akerman en Adam DeVine\r\n\r\nEen middelbare scholier wordt samen met haar vrienden op mysterieuze wijze getransporteerd naar een horrorfilm \r\nuit 1980. Het betreft een film waarin haar overleden moeder, een gevierde 'scream queen', een rol speelde. Herenigd \r\nmet haar moeder moet ze samen met haar vrienden avances van kampbegeleiders zien te weren, de strijd aangaan \r\nmet een maniakale moordenaar en een manier vinden om te ontsnappen en veilig terug naar huis te keren.\r\n\r\nDeze review wordt u aangeboden door\r\n\r\nDUTCH MOVIE THEATER","torrent":{"xt":"urn:btih:3a1df0f436c246d55727bccecd39e80f7b9a24e9","amp;dn":"The+Final+Girls+%282015%29+WEB-DL+%28xvid%29+NL+Subs.+DMT+","amp;tr":["udp%3A%2F%2Ftracker.leechers-paradise.org%3A6969","udp%3A%2F%2Fzer0day.ch%3A1337","udp%3A%2F%2Fopen.demonii.com%3A1337","udp%3A%2F%2Ftracker.coppersurfer.tk%3A6969","udp%3A%2F%2Fexodus.desync.com%3A6969"],"infoHash":"3a1df0f436c246d55727bccecd39e80f7b9a24e9","infoHashBuffer":{"type":"Buffer","data":[58,29,240,244,54,194,70,213,87,39,188,206,205,57,232,15,123,154,36,233]},"announce":[],"urlList":[]}}