{"title":"Halloween.II.2009.iTALiAN.DVDRip.XviD-TRL[bt-torrentitalia.org]","uid":5294850,"size":1467719680,"categoryP":"video","categoryS":"movies","magnet":"?xt=urn:btih:5b8ed6674b62300500802c6b94f63768ea495de7&amp;dn=Halloween.II.2009.iTALiAN.DVDRip.XviD-TRL%5Bbt-torrentitalia.org%5D&amp;tr=udp%3A%2F%2Ftracker.openbittorrent.com%3A80&amp;tr=udp%3A%2F%2Fopen.demonii.com%3A1337&amp;tr=udp%3A%2F%2Ftracker.coppersurfer.tk%3A6969&amp;tr=udp%3A%2F%2Fexodus.desync.com%3A6969","seeders":0,"leechers":1,"uploader":"bt-italiantorrent","files":2,"time":1264021334,"description":"PER SCARICARE QUESTO FILE BISOGNA ESSERE REGISTRATI SU\n\n  &lt;a href=&quot;\nhttp://bt-italiatorrent.org/&quot; rel=&quot;nofollow&quot; target=&quot;_NEW&quot;&gt;\nhttp://bt-italiatorrent.org/&lt;/a&gt;\n\nINOLTRE TROVERETE TANTI DVDR DVDRIP GAMES ECT.. IN ANTEPRIMA\n\nTitolo originale: Halloween II\nNazione: U.S.A.\nAnno: 2009\nGenere: Horror\nDurata: 105'\nRegia: Rob Zombie\nSito ufficiale: www.halloween2-movie.com\nSito italiano: www.halloween2.it\n\n\nCast: Sheri Moon Zombie, Chase Wright Vanek, Scout Taylor-Compton, Brad Dourif, Caroline Williams, Malcolm McDowell, Tyler Mane, Dayton Callie\nProduzione: Dimension Films, Spectacle Entertainment Group, Trancas International Films\nDistribuzione: Mediafilm\nData di uscita: 16 Ottobre 2009 (cinema)\n\nTrama:\nAlcune questioni familiari rimaste in sospeso, sono il pretesto per Michael Myers, per fare ritorno nella cittadina di Haddonfield, nell'Illinois. Siamo di nuovo ad Halloween, e per gli abitanti della cittadina sta per scatenarsi una nuova ondata di paura e violenza\n\n\n\n","torrent":{"xt":"urn:btih:5b8ed6674b62300500802c6b94f63768ea495de7","amp;dn":"Halloween.II.2009.iTALiAN.DVDRip.XviD-TRL%5Bbt-torrentitalia.org%5D","amp;tr":["udp%3A%2F%2Ftracker.openbittorrent.com%3A80","udp%3A%2F%2Fopen.demonii.com%3A1337","udp%3A%2F%2Ftracker.coppersurfer.tk%3A6969","udp%3A%2F%2Fexodus.desync.com%3A6969"],"infoHash":"5b8ed6674b62300500802c6b94f63768ea495de7","infoHashBuffer":{"type":"Buffer","data":[91,142,214,103,75,98,48,5,0,128,44,107,148,246,55,104,234,73,93,231]},"announce":[],"urlList":[]}}