{"title":"Pearl The Assassin 2015 HDRip XviD AC3-EVO","uid":12541310,"size":1438839488,"categoryP":"video","categoryS":"movies","magnet":"?xt=urn:btih:67ab434ace0905f78c3d18b5330b89ed67b1a62e&amp;dn=Pearl+The+Assassin+2015+HDRip+XviD+AC3-EVO&amp;tr=udp%3A%2F%2Ftracker.leechers-paradise.org%3A6969&amp;tr=udp%3A%2F%2Fzer0day.ch%3A1337&amp;tr=udp%3A%2F%2Fopen.demonii.com%3A1337&amp;tr=udp%3A%2F%2Ftracker.coppersurfer.tk%3A6969&amp;tr=udp%3A%2F%2Fexodus.desync.com%3A6969","seeders":0,"leechers":1,"uploader":"hotpena","files":4,"time":1444400879,"description":"\nCOVER: \nhttp://icezap.com/img-5617b3b3a4ae6.html\n\nPLOT: \nConsumed by a horrific event in her past, a woman is driven to seek violent justice, but as the blood spills and the body count rises, will Pearl ever really be satisfied?\n\nRELEASED: \n June 2015 \n\nIMDB: http://www.imdb.com/title/tt4797534/\n\n\n\n Size: 38342656 bytes (36.57 MiB), duration: 00:01:51, avg.bitrate: 2763 kb/s\nAudio: ac3, 48000 Hz, stereo, 192 kb/s\nVideo: mpeg4, yuv420p, 720x400, 25.00 fps(r)\n\n\n\n\n Size: 1400496128 bytes (1.30 GiB), duration: 01:18:26, avg.bitrate: 2381 kb/s\nAudio: ac3, 48000 Hz, stereo, 192 kb/s\nVideo: mpeg4, yuv420p, 720x400, 25.00 fps(r)\n \nhttp://icezap.com/img-5617b3b41e75e.html\n \nhttp://icezap.com/img-5617b3b4210e1.html\n \nhttp://icezap.com/img-5617b3b4236d9.html\n\n\nDOWNLOAD AND ENJOY. \n\n KEEP IT FOR LONG SEEDING TO HELP OTHERS \n\n \n Thanks to : EVO\n Movie Share","torrent":{"xt":"urn:btih:67ab434ace0905f78c3d18b5330b89ed67b1a62e","amp;dn":"Pearl+The+Assassin+2015+HDRip+XviD+AC3-EVO","amp;tr":["udp%3A%2F%2Ftracker.leechers-paradise.org%3A6969","udp%3A%2F%2Fzer0day.ch%3A1337","udp%3A%2F%2Fopen.demonii.com%3A1337","udp%3A%2F%2Ftracker.coppersurfer.tk%3A6969","udp%3A%2F%2Fexodus.desync.com%3A6969"],"infoHash":"67ab434ace0905f78c3d18b5330b89ed67b1a62e","infoHashBuffer":{"type":"Buffer","data":[103,171,67,74,206,9,5,247,140,61,24,181,51,11,137,237,103,177,166,46]},"announce":[],"urlList":[]}}