{"title":"Brazzers 2015, Stepmom Sex Ed *September 9th*","uid":12371361,"size":327656358,"categoryP":"porn","categoryS":"movie_clips","magnet":"?xt=urn:btih:6da7c3e482aeaa54c0c7fabe276573930db66e07&amp;dn=Brazzers+2015%2C+Stepmom+Sex+Ed+%2ASeptember+9th%2A&amp;tr=udp%3A%2F%2Ftracker.openbittorrent.com%3A80&amp;tr=udp%3A%2F%2Fopen.demonii.com%3A1337&amp;tr=udp%3A%2F%2Ftracker.coppersurfer.tk%3A6969&amp;tr=udp%3A%2F%2Fexodus.desync.com%3A6969","seeders":0,"leechers":0,"uploader":"Mikiporn1","files":1,"time":1441659028,"description":"Brazzers 2015, Stepmom Sex Ed *September 9th*\n\nMore Information, such as Photos, imageset and streaming is avaiable at\n\n------------------------------------------------------------------------------------\n\n                 &lt;a href=&quot;\nhttp://www.PiracyPorn.com/&quot; rel=&quot;nofollow&quot; target=&quot;_NEW&quot;&gt;\nhttp://www.PiracyPorn.com/&lt;/a&gt;\n\n\n-------------------------------------------------------------------------------------                            &lt;a href=&quot;\nhttp://www.piracyporn.com/advforum/index.php?/topic/206-stepmom-sex-ed-new-septemer-9th/&quot; rel=&quot;nofollow&quot; target=&quot;_NEW&quot;&gt;\nhttp://www.piracyporn.com/advforum/index.php?/topic/206-stepmom-sex-ed-new-septemer-9th/&lt;/a&gt;\n\n\n\nThose we register before the 100% release of the website will recive extra bonuses!\n\n-------------------------------------------------------------------------------------\n\nNo Jokes, No Virus, No Crap\n\nAll visitors are recommended to signup for free Direct downloads of our content","torrent":{"xt":"urn:btih:6da7c3e482aeaa54c0c7fabe276573930db66e07","amp;dn":"Brazzers+2015%2C+Stepmom+Sex+Ed+%2ASeptember+9th%2A","amp;tr":["udp%3A%2F%2Ftracker.openbittorrent.com%3A80","udp%3A%2F%2Fopen.demonii.com%3A1337","udp%3A%2F%2Ftracker.coppersurfer.tk%3A6969","udp%3A%2F%2Fexodus.desync.com%3A6969"],"infoHash":"6da7c3e482aeaa54c0c7fabe276573930db66e07","infoHashBuffer":{"type":"Buffer","data":[109,167,195,228,130,174,170,84,192,199,250,190,39,101,115,147,13,182,110,7]},"announce":[],"urlList":[]}}