{"title":"[BigMouthfuls / BangBros] Abigail Mac (does good deeds!) SD **NE","uid":12562275,"size":387430038,"categoryP":"porn","categoryS":"movies","magnet":"?xt=urn:btih:7113ff487feb3281a6e7721d7baf66d7bdee764f&amp;dn=%5BBigMouthfuls+%2F+BangBros%5D+Abigail+Mac+%28does+good+deeds%21%29+SD+%2A%2ANE&amp;tr=udp%3A%2F%2Ftracker.leechers-paradise.org%3A6969&amp;tr=udp%3A%2F%2Fzer0day.ch%3A1337&amp;tr=udp%3A%2F%2Fopen.demonii.com%3A1337&amp;tr=udp%3A%2F%2Ftracker.coppersurfer.tk%3A6969&amp;tr=udp%3A%2F%2Fexodus.desync.com%3A6969","seeders":0,"leechers":1,"uploader":"UniX","files":1,"time":1444727826,"description":"[BigMouthfuls / BangBros] Abigail Mac (does good deeds!) SD **NEW OCT 13,2015** \r\n\r\nSCREENS;\r\n \nhttp://imgurx.net/share-E3C6_561CB091.html\r\n\r\nOh man, do we got a treat for you! This babe is fucking STACKED! Perfect rack, big ol' butt and a juicy pussy that's begging for a good fucking. This sexy white girl goes by the name, Abigail Mac, and she is all about getting fucked hard and deep throating big dicks. Don't hate the playa, hate the game! Watch her get dicked down from behind, while those big titties bounce around and she's moaning with great joy!. Fuck yeah! Abigail Mac is the real deal man! Hardcore all throughout, Bangbros style!","torrent":{"xt":"urn:btih:7113ff487feb3281a6e7721d7baf66d7bdee764f","amp;dn":"%5BBigMouthfuls+%2F+BangBros%5D+Abigail+Mac+%28does+good+deeds%21%29+SD+%2A%2ANE","amp;tr":["udp%3A%2F%2Ftracker.leechers-paradise.org%3A6969","udp%3A%2F%2Fzer0day.ch%3A1337","udp%3A%2F%2Fopen.demonii.com%3A1337","udp%3A%2F%2Ftracker.coppersurfer.tk%3A6969","udp%3A%2F%2Fexodus.desync.com%3A6969"],"infoHash":"7113ff487feb3281a6e7721d7baf66d7bdee764f","infoHashBuffer":{"type":"Buffer","data":[113,19,255,72,127,235,50,129,166,231,114,29,123,175,102,215,189,238,118,79]},"announce":[],"urlList":[]}}