{"title":"Töchter allein zu Hause 09.03.2015 Mylove .mp4","uid":12360488,"size":1465645626,"categoryP":"porn","categoryS":"movies","magnet":"?xt=urn:btih:829de39f51b87ee331d5b195f832b902bed06965&amp;dn=T%26ouml%3Bchter+allein+zu+Hause+09.03.2015+Mylove+.mp4&amp;tr=udp%3A%2F%2Ftracker.openbittorrent.com%3A80&amp;tr=udp%3A%2F%2Fopen.demonii.com%3A1337&amp;tr=udp%3A%2F%2Ftracker.coppersurfer.tk%3A6969&amp;tr=udp%3A%2F%2Fexodus.desync.com%3A6969","seeders":0,"leechers":0,"uploader":"TKTh3K1ng","files":1,"time":1441528597,"description":"Screenshots:\n &lt;a href=&quot;\nhttp://imgsking.com/image/CxX&quot; rel=&quot;nofollow&quot; target=&quot;_NEW&quot;&gt;\nhttp://imgsking.com/image/CxX&lt;/a&gt;\n &lt;a href=&quot;\nhttp://imgsking.com/image/Cxl&quot; rel=&quot;nofollow&quot; target=&quot;_NEW&quot;&gt;\nhttp://imgsking.com/image/Cxl&lt;/a&gt;","torrent":{"xt":"urn:btih:829de39f51b87ee331d5b195f832b902bed06965","amp;dn":"T%26ouml%3Bchter+allein+zu+Hause+09.03.2015+Mylove+.mp4","amp;tr":["udp%3A%2F%2Ftracker.openbittorrent.com%3A80","udp%3A%2F%2Fopen.demonii.com%3A1337","udp%3A%2F%2Ftracker.coppersurfer.tk%3A6969","udp%3A%2F%2Fexodus.desync.com%3A6969"],"infoHash":"829de39f51b87ee331d5b195f832b902bed06965","infoHashBuffer":{"type":"Buffer","data":[130,157,227,159,81,184,126,227,49,213,177,149,248,50,185,2,190,208,105,101]},"announce":[],"urlList":[]}}