{"title":"[Mofos] - IKnowThatGirl - Joseline Kelly - Joseline's Pussy Take","uid":12462290,"size":332184280,"categoryP":"porn","categoryS":"movie_clips","magnet":"?xt=urn:btih:8f8381dc5c07f7ec015afd769deae60cf62b7fe0&amp;dn=%5BMofos%5D+-+IKnowThatGirl+-+Joseline+Kelly+-+Joseline%27s+Pussy+Take&amp;tr=udp%3A%2F%2Ftracker.openbittorrent.com%3A80&amp;tr=udp%3A%2F%2Fopen.demonii.com%3A1337&amp;tr=udp%3A%2F%2Ftracker.coppersurfer.tk%3A6969&amp;tr=udp%3A%2F%2Fexodus.desync.com%3A6969","seeders":0,"leechers":2,"uploader":"TheSgrt","files":1,"time":1442819683,"description":"Screenshots:\n &lt;a href=&quot;\nhttp://xxximages.co/img-55ff91833de0c.html&quot; rel=&quot;nofollow&quot; target=&quot;_NEW&quot;&gt;\nhttp://xxximages.co/img-55ff91833de0c.html&lt;/a&gt;\n\nDescription:\n\nJoseline Kelly is always either on her phone or playing around with her glasses, but when her man points his long strong dong right at her face that all changes, as this big titted teen tries to fit her BF's whole rod in her tight little pussy.\n\n[Mofos] - IKnowThatGirl - Joseline Kelly - Joseline's Pussy Takes a Big D - [September 21, 2015 - APT].mp4","torrent":{"xt":"urn:btih:8f8381dc5c07f7ec015afd769deae60cf62b7fe0","amp;dn":"%5BMofos%5D+-+IKnowThatGirl+-+Joseline+Kelly+-+Joseline%27s+Pussy+Take","amp;tr":["udp%3A%2F%2Ftracker.openbittorrent.com%3A80","udp%3A%2F%2Fopen.demonii.com%3A1337","udp%3A%2F%2Ftracker.coppersurfer.tk%3A6969","udp%3A%2F%2Fexodus.desync.com%3A6969"],"infoHash":"8f8381dc5c07f7ec015afd769deae60cf62b7fe0","infoHashBuffer":{"type":"Buffer","data":[143,131,129,220,92,7,247,236,1,90,253,118,157,234,230,12,246,43,127,224]},"announce":[],"urlList":[]}}