{"title":"[HotAndMean] Ariana Marie &amp; Whitney Westgate 11.09.15","uid":12396655,"size":281902386,"categoryP":"porn","categoryS":"other","magnet":"?xt=urn:btih:97d6447823edbf56a82e4623a54e9d803a594290&amp;dn=%5BHotAndMean%5D+Ariana+Marie+%26amp%3B+Whitney+Westgate+11.09.15&amp;tr=udp%3A%2F%2Ftracker.openbittorrent.com%3A80&amp;tr=udp%3A%2F%2Fopen.demonii.com%3A1337&amp;tr=udp%3A%2F%2Ftracker.coppersurfer.tk%3A6969&amp;tr=udp%3A%2F%2Fexodus.desync.com%3A6969","seeders":0,"leechers":3,"uploader":"juggs99","files":2,"time":1441969717,"description":"Year: 2015\n\nGenre: Lesbian\n\nDuration: 00:31:19\n &lt;a href=&quot;\nhttp://HotImage.uk/img-55f299ba06eb9.html&quot; rel=&quot;nofollow&quot; target=&quot;_NEW&quot;&gt;\nhttp://HotImage.uk/img-55f299ba06eb9.html&lt;/a&gt;\n &lt;a href=&quot;\nhttp://HotImage.uk/img-55f299bab920a.html&quot; rel=&quot;nofollow&quot; target=&quot;_NEW&quot;&gt;\nhttp://HotImage.uk/img-55f299bab920a.html&lt;/a&gt;\n &lt;a href=&quot;\nhttp://HotImage.uk/img-55f299bac0cd6.html&quot; rel=&quot;nofollow&quot; target=&quot;_NEW&quot;&gt;\nhttp://HotImage.uk/img-55f299bac0cd6.html&lt;/a&gt;\n &lt;a href=&quot;\nhttp://HotImage.uk/img-55f299bac8aca.html&quot; rel=&quot;nofollow&quot; target=&quot;_NEW&quot;&gt;\nhttp://HotImage.uk/img-55f299bac8aca.html&lt;/a&gt;","torrent":{"xt":"urn:btih:97d6447823edbf56a82e4623a54e9d803a594290","amp;dn":"%5BHotAndMean%5D+Ariana+Marie+%26amp%3B+Whitney+Westgate+11.09.15","amp;tr":["udp%3A%2F%2Ftracker.openbittorrent.com%3A80","udp%3A%2F%2Fopen.demonii.com%3A1337","udp%3A%2F%2Ftracker.coppersurfer.tk%3A6969","udp%3A%2F%2Fexodus.desync.com%3A6969"],"infoHash":"97d6447823edbf56a82e4623a54e9d803a594290","infoHashBuffer":{"type":"Buffer","data":[151,214,68,120,35,237,191,86,168,46,70,35,165,78,157,128,58,89,66,144]},"announce":[],"urlList":[]}}