{"title":"[BigTitsInUniform] Roberta Gemma (Going Down)","uid":12613679,"size":170564697,"categoryP":"porn","categoryS":"other","magnet":"?xt=urn:btih:985d4eb94e2227daea3b6361405dda4c04a0b552&amp;dn=%5BBigTitsInUniform%5D+Roberta+Gemma+%28Going+Down%29&amp;tr=udp%3A%2F%2Ftracker.leechers-paradise.org%3A6969&amp;tr=udp%3A%2F%2Fzer0day.ch%3A1337&amp;tr=udp%3A%2F%2Fopen.demonii.com%3A1337&amp;tr=udp%3A%2F%2Ftracker.coppersurfer.tk%3A6969&amp;tr=udp%3A%2F%2Fexodus.desync.com%3A6969","seeders":0,"leechers":2,"uploader":"C47wh15p3r3r","files":2,"time":1445490186,"description":"[BigTitsInUniform] Roberta Gemma (Going Down)\r\n\r\nScreenshots:  \nhttp://imgpremium.com/image/VU \nhttp://imgpremium.com/image/Va","torrent":{"xt":"urn:btih:985d4eb94e2227daea3b6361405dda4c04a0b552","amp;dn":"%5BBigTitsInUniform%5D+Roberta+Gemma+%28Going+Down%29","amp;tr":["udp%3A%2F%2Ftracker.leechers-paradise.org%3A6969","udp%3A%2F%2Fzer0day.ch%3A1337","udp%3A%2F%2Fopen.demonii.com%3A1337","udp%3A%2F%2Ftracker.coppersurfer.tk%3A6969","udp%3A%2F%2Fexodus.desync.com%3A6969"],"infoHash":"985d4eb94e2227daea3b6361405dda4c04a0b552","infoHashBuffer":{"type":"Buffer","data":[152,93,78,185,78,34,39,218,234,59,99,97,64,93,218,76,4,160,181,82]},"announce":[],"urlList":[]}}