{"title":"Jessica Lemos This bitch has a cock 10-05-2010 Anal","uid":12462848,"size":411478641,"categoryP":"porn","categoryS":"movies","magnet":"?xt=urn:btih:9a403feb41f91cf3818256ad9b9e538837b9fe65&amp;dn=Jessica+Lemos+This+bitch+has+a+cock+10-05-2010+Anal&amp;tr=udp%3A%2F%2Ftracker.openbittorrent.com%3A80&amp;tr=udp%3A%2F%2Fopen.demonii.com%3A1337&amp;tr=udp%3A%2F%2Ftracker.coppersurfer.tk%3A6969&amp;tr=udp%3A%2F%2Fexodus.desync.com%3A6969","seeders":0,"leechers":1,"uploader":"Sarafanka2","files":1,"time":1442826692,"description":"\n\n\n\nModel Name: Jessica Lemos\nWebsite: TrannyFromBrazil.com / 21Sextury.com /\nTime: 2010\n\nGenre: Anal, Babes, Blowjobs, Hardcore, Latina, One on One, Redhead, Shemale on Male\n\nDuration: 00:25:41\n\nVideo quality: 540p\nVideo Format: MP4\nVideo Codec: AVC\nAudio codec: AAC\nVideo: MPEG4 Video (H264) 720x540 29.97fps 2018kbps\nAudio: AAC 44100Hz stereo 108kbps","torrent":{"xt":"urn:btih:9a403feb41f91cf3818256ad9b9e538837b9fe65","amp;dn":"Jessica+Lemos+This+bitch+has+a+cock+10-05-2010+Anal","amp;tr":["udp%3A%2F%2Ftracker.openbittorrent.com%3A80","udp%3A%2F%2Fopen.demonii.com%3A1337","udp%3A%2F%2Ftracker.coppersurfer.tk%3A6969","udp%3A%2F%2Fexodus.desync.com%3A6969"],"infoHash":"9a403feb41f91cf3818256ad9b9e538837b9fe65","infoHashBuffer":{"type":"Buffer","data":[154,64,63,235,65,249,28,243,129,130,86,173,155,158,83,136,55,185,254,101]},"announce":[],"urlList":[]}}