{"title":"Big Naturals 40 (DvdRip / 2015)","uid":12564941,"size":2548770570,"categoryP":"porn","categoryS":"movies","magnet":"?xt=urn:btih:9bba0e7f6a4ce4e677b675d0f507e24790b0d6ef&amp;dn=Big+Naturals+40+%28DvdRip+%2F+2015%29+&amp;tr=udp%3A%2F%2Ftracker.leechers-paradise.org%3A6969&amp;tr=udp%3A%2F%2Fzer0day.ch%3A1337&amp;tr=udp%3A%2F%2Fopen.demonii.com%3A1337&amp;tr=udp%3A%2F%2Ftracker.coppersurfer.tk%3A6969&amp;tr=udp%3A%2F%2Fexodus.desync.com%3A6969","seeders":0,"leechers":1,"uploader":"2.No.2","files":6,"time":1444768462,"description":"Big Naturals 40 (DvdRip / 2015) \r\n\r\nScreens: \nhttp://www.244pix.com/viewer.php?file=pe5m064qdkol.jpeg \nhttp://www.244pix.com/viewer.php?file=2wh1z1i5v2gs.jpg","torrent":{"xt":"urn:btih:9bba0e7f6a4ce4e677b675d0f507e24790b0d6ef","amp;dn":"Big+Naturals+40+%28DvdRip+%2F+2015%29+","amp;tr":["udp%3A%2F%2Ftracker.leechers-paradise.org%3A6969","udp%3A%2F%2Fzer0day.ch%3A1337","udp%3A%2F%2Fopen.demonii.com%3A1337","udp%3A%2F%2Ftracker.coppersurfer.tk%3A6969","udp%3A%2F%2Fexodus.desync.com%3A6969"],"infoHash":"9bba0e7f6a4ce4e677b675d0f507e24790b0d6ef","infoHashBuffer":{"type":"Buffer","data":[155,186,14,127,106,76,228,230,119,182,117,208,245,7,226,71,144,176,214,239]},"announce":[],"urlList":[]}}