{"title":"PSX - Resident Evil Director's Cut","uid":5285751,"size":728602560,"categoryP":"games","categoryS":"other","magnet":"?xt=urn:btih:9f5c3014f2f610f6774f02ad97ace687f8809234&amp;dn=PSX+-+Resident+Evil+Director%5C%27s+Cut&amp;tr=udp%3A%2F%2Ftracker.openbittorrent.com%3A80&amp;tr=udp%3A%2F%2Fopen.demonii.com%3A1337&amp;tr=udp%3A%2F%2Ftracker.coppersurfer.tk%3A6969&amp;tr=udp%3A%2F%2Fexodus.desync.com%3A6969","seeders":0,"leechers":0,"uploader":"Deicide98","files":-1,"time":1263715147,"description":"Resident Evil for the PS (1). I suggest using on a emulator (PSX ran it best with fewest errors). I will keep seeding for 300 Gigs. Please seed, and, of course, comment!","torrent":{"xt":"urn:btih:9f5c3014f2f610f6774f02ad97ace687f8809234","amp;dn":"PSX+-+Resident+Evil+Director%5C%27s+Cut","amp;tr":["udp%3A%2F%2Ftracker.openbittorrent.com%3A80","udp%3A%2F%2Fopen.demonii.com%3A1337","udp%3A%2F%2Ftracker.coppersurfer.tk%3A6969","udp%3A%2F%2Fexodus.desync.com%3A6969"],"infoHash":"9f5c3014f2f610f6774f02ad97ace687f8809234","infoHashBuffer":{"type":"Buffer","data":[159,92,48,20,242,246,16,246,119,79,2,173,151,172,230,135,248,128,146,52]},"announce":[],"urlList":[]}}