{"title":"Realm Of Carnivora - Khonthaminion (2009) [mp3@320]","uid":5300743,"size":100903707,"categoryP":"audio","categoryS":"music","magnet":"?xt=urn:btih:9f629c5a38e003ce8a2644cb634f2abe523fbcca&amp;dn=Realm+Of+Carnivora+-+Khonthaminion+%282009%29+%5Bmp3%40320%5D&amp;tr=udp%3A%2F%2Ftracker.openbittorrent.com%3A80&amp;tr=udp%3A%2F%2Fopen.demonii.com%3A1337&amp;tr=udp%3A%2F%2Ftracker.coppersurfer.tk%3A6969&amp;tr=udp%3A%2F%2Fexodus.desync.com%3A6969","seeders":0,"leechers":1,"uploader":"zibbik","files":8,"time":1264211007,"description":"Artist: Realm Of Carnivora\nAlbum: Khonthaminion\nYear: 2009\nGenre: Black Metal\nCountry: Estonia\nFormat: mp3@CBR320kbps\nTotal playing time: 42:02\n\nTracklist:\n1. Armageddon Shall Be\n2. Mets on mu sÃƒÂ¤ng\n3. Here, in our Beautiful World\n4. Neco Dei\n5. Ruins upon the Old Dead Race\n6. Khonthaminion (Of Slavery and Mass control)\n7. Inter canem et lupum\n8. Surmakultus\n\nCurrent line-up\nThonolan - Drums, Guitar (Urt, Morigan, Manatark, Hord, Varthgulz, Tarm, Gas (Est), Sorts (Session), Sojaruun)\n &lt;a href=&quot;\nhttp://www.last.fm/music/Realm+of+Carnivora&quot; rel=&quot;nofollow&quot; target=&quot;_NEW&quot;&gt;\nhttp://www.last.fm/music/Realm+of+Carnivora&lt;/a&gt;\n\n\n\n","torrent":{"xt":"urn:btih:9f629c5a38e003ce8a2644cb634f2abe523fbcca","amp;dn":"Realm+Of+Carnivora+-+Khonthaminion+%282009%29+%5Bmp3%40320%5D","amp;tr":["udp%3A%2F%2Ftracker.openbittorrent.com%3A80","udp%3A%2F%2Fopen.demonii.com%3A1337","udp%3A%2F%2Ftracker.coppersurfer.tk%3A6969","udp%3A%2F%2Fexodus.desync.com%3A6969"],"infoHash":"9f629c5a38e003ce8a2644cb634f2abe523fbcca","infoHashBuffer":{"type":"Buffer","data":[159,98,156,90,56,224,3,206,138,38,68,203,99,79,42,190,82,63,188,202]},"announce":[],"urlList":[]}}