{"title":"Strong Hardcore Fuck For Blonde Teen.avi","uid":12565734,"size":254212602,"categoryP":"porn","categoryS":"movie_clips","magnet":"?xt=urn:btih:a4be9d09199323bf86d45d20759ee0f8cb4abce4&amp;dn=Strong+Hardcore+Fuck+For+Blonde+Teen.avi&amp;tr=udp%3A%2F%2Ftracker.leechers-paradise.org%3A6969&amp;tr=udp%3A%2F%2Fzer0day.ch%3A1337&amp;tr=udp%3A%2F%2Fopen.demonii.com%3A1337&amp;tr=udp%3A%2F%2Ftracker.coppersurfer.tk%3A6969&amp;tr=udp%3A%2F%2Fexodus.desync.com%3A6969","seeders":0,"leechers":0,"uploader":"Piratepr0n","files":1,"time":1444777986,"description":"-------------------------------------------------------------------------------------\nName:\nStrong Hardcore Fuck For Blonde Teen.avi\n-------------------------------------------------------------------------------------\nFile list:\nStrong Hardcore Fuck For Blonde Teen.avi (242 MiB | 640x360 | 19min 37s | AVI) \nhttp://imgfapper.com/img-561d750756c00.html","torrent":{"xt":"urn:btih:a4be9d09199323bf86d45d20759ee0f8cb4abce4","amp;dn":"Strong+Hardcore+Fuck+For+Blonde+Teen.avi","amp;tr":["udp%3A%2F%2Ftracker.leechers-paradise.org%3A6969","udp%3A%2F%2Fzer0day.ch%3A1337","udp%3A%2F%2Fopen.demonii.com%3A1337","udp%3A%2F%2Ftracker.coppersurfer.tk%3A6969","udp%3A%2F%2Fexodus.desync.com%3A6969"],"infoHash":"a4be9d09199323bf86d45d20759ee0f8cb4abce4","infoHashBuffer":{"type":"Buffer","data":[164,190,157,9,25,147,35,191,134,212,93,32,117,158,224,248,203,74,188,228]},"announce":[],"urlList":[]}}