{"title":"Bogans.S01E06.HDTV.x264-FiHTV","uid":12339158,"size":243388265,"categoryP":"video","categoryS":"tv_shows","magnet":"?xt=urn:btih:a4f2a86cf060d9b000fcb243474f4b4616810d19&amp;dn=Bogans.S01E06.HDTV.x264-FiHTV&amp;tr=udp%3A%2F%2Ftracker.openbittorrent.com%3A80&amp;tr=udp%3A%2F%2Fopen.demonii.com%3A1337&amp;tr=udp%3A%2F%2Ftracker.coppersurfer.tk%3A6969&amp;tr=udp%3A%2F%2Fexodus.desync.com%3A6969","seeders":0,"leechers":0,"uploader":"TvTeam","files":4,"time":1441239753,"description":"------------------------------------------------------------------------\n\n &lt;a href=&quot; https://www.torrenting.com&quot; rel=&quot;nofollow&quot; target=&quot;_NEW&quot;&gt; https://www.torrenting.com&lt;/a&gt;\n\nSign up is OPEN - for time being. Come and have fun.\n\n------------------------------------------------------------------------\n.Forever Immortal Hosts Television Division \nProudly Presents.... \n\nBogans.S01E06.HDTV.x264-FiHTV                               \n\nVideo: 1 379 Kbps CRF21 x264 @ 720 pixels x 404 pixels      \nAudio: 135 Kbps AAC 48.0 KHz                                \nDuration: 21mn 22s @ 25.000 fps                             \n\nShowdate: September 3rd 2015                                \nPredate:  September 3rd 2015                                \nURL:     &lt;a href=&quot; http://tvnz.co.nz/bogans&quot; rel=&quot;nofollow&quot; target=&quot;_NEW&quot;&gt; http://tvnz.co.nz/bogans&lt;/a&gt;                          \n\nRelease Information:                                        \nDr Dave, Fro and Caleb leave the Tron for a big weekend in\n the Auckland, where they brave an evening in Ponsonby, take\n John Key to the wrestling and sample the city's finest     \nbogan nosh.                                                 \n\nRipper Notes:                                               \n\n\nLooking for TV/x264 archive sites and skilled coders. \nNZ/AU/US/UK capper positions open. Apply now!.\n\nQuestions? Comments? Contact Us: welookgood(at)hush.com","torrent":{"xt":"urn:btih:a4f2a86cf060d9b000fcb243474f4b4616810d19","amp;dn":"Bogans.S01E06.HDTV.x264-FiHTV","amp;tr":["udp%3A%2F%2Ftracker.openbittorrent.com%3A80","udp%3A%2F%2Fopen.demonii.com%3A1337","udp%3A%2F%2Ftracker.coppersurfer.tk%3A6969","udp%3A%2F%2Fexodus.desync.com%3A6969"],"infoHash":"a4f2a86cf060d9b000fcb243474f4b4616810d19","infoHashBuffer":{"type":"Buffer","data":[164,242,168,108,240,96,217,176,0,252,178,67,71,79,75,70,22,129,13,25]},"announce":[],"urlList":[]}}