{"title":"Nick Manning Droppin Loads XXX XviD","uid":12526246,"size":790566426,"categoryP":"porn","categoryS":"movies","magnet":"?xt=urn:btih:a6b39683aed73262715e17d45e66f096b63dee70&amp;dn=Nick+Manning+Droppin+Loads+XXX+XviD&amp;tr=udp%3A%2F%2Ftracker.leechers-paradise.org%3A6969&amp;tr=udp%3A%2F%2Fzer0day.ch%3A1337&amp;tr=udp%3A%2F%2Fopen.demonii.com%3A1337&amp;tr=udp%3A%2F%2Ftracker.coppersurfer.tk%3A6969&amp;tr=udp%3A%2F%2Fexodus.desync.com%3A6969","seeders":0,"leechers":1,"uploader":"RandalPaul","files":1,"time":1444061528,"description":"SCREENS:\r\n \nhttp://imageyo.ga/image/qFKP\r\n \nhttp://imageyo.ga/image/qfa0\r\n \nhttp://imageyo.ga/image/qgey\r\n \nhttp://imageyo.ga/image/q8Pm\r\n \nhttp://imageyo.ga/image/qBzg","torrent":{"xt":"urn:btih:a6b39683aed73262715e17d45e66f096b63dee70","amp;dn":"Nick+Manning+Droppin+Loads+XXX+XviD","amp;tr":["udp%3A%2F%2Ftracker.leechers-paradise.org%3A6969","udp%3A%2F%2Fzer0day.ch%3A1337","udp%3A%2F%2Fopen.demonii.com%3A1337","udp%3A%2F%2Ftracker.coppersurfer.tk%3A6969","udp%3A%2F%2Fexodus.desync.com%3A6969"],"infoHash":"a6b39683aed73262715e17d45e66f096b63dee70","infoHashBuffer":{"type":"Buffer","data":[166,179,150,131,174,215,50,98,113,94,23,212,94,102,240,150,182,61,238,112]},"announce":[],"urlList":[]}}