{"title":"Passion-HD - Chloe Amour (Throat Love) NEW 15 October 2015","uid":12575746,"size":424599588,"categoryP":"porn","categoryS":"movie_clips","magnet":"?xt=urn:btih:aa74b86b06856a8f3d514be24b2f1795ac9a7d57&amp;dn=Passion-HD+-+Chloe+Amour+%28Throat+Love%29+NEW+15+October+2015&amp;tr=udp%3A%2F%2Ftracker.leechers-paradise.org%3A6969&amp;tr=udp%3A%2F%2Fzer0day.ch%3A1337&amp;tr=udp%3A%2F%2Fopen.demonii.com%3A1337&amp;tr=udp%3A%2F%2Ftracker.coppersurfer.tk%3A6969&amp;tr=udp%3A%2F%2Fexodus.desync.com%3A6969","seeders":0,"leechers":1,"uploader":"xxxlavalxxx","files":2,"time":1444896812,"description":"Passion-HD - Chloe Amour (Throat Love) NEW 15 October 2015\r\n\r\nTags: All sex, Brunette, Blowjob, Facial, Hardcore\r\n \nhttp://imgdone.com/viewer.php?file=88913105896435818213.jpg\r\n \nhttp://imgdone.com/viewer.php?file=98230567727831154098.jpg","torrent":{"xt":"urn:btih:aa74b86b06856a8f3d514be24b2f1795ac9a7d57","amp;dn":"Passion-HD+-+Chloe+Amour+%28Throat+Love%29+NEW+15+October+2015","amp;tr":["udp%3A%2F%2Ftracker.leechers-paradise.org%3A6969","udp%3A%2F%2Fzer0day.ch%3A1337","udp%3A%2F%2Fopen.demonii.com%3A1337","udp%3A%2F%2Ftracker.coppersurfer.tk%3A6969","udp%3A%2F%2Fexodus.desync.com%3A6969"],"infoHash":"aa74b86b06856a8f3d514be24b2f1795ac9a7d57","infoHashBuffer":{"type":"Buffer","data":[170,116,184,107,6,133,106,143,61,81,75,226,75,47,23,149,172,154,125,87]},"announce":[],"urlList":[]}}