{"title":"Myfirstsexteacher Jewels Jade - Chad White HD 1080p","uid":12518198,"size":2984486436,"categoryP":"porn","categoryS":"hd___movies","magnet":"?xt=urn:btih:aaa2a67e10b85d5c7927e456c4ae55bbbf44e7b6&amp;dn=Myfirstsexteacher+Jewels+Jade+-+Chad+White+HD+1080p&amp;tr=udp%3A%2F%2Ftracker.leechers-paradise.org%3A6969&amp;tr=udp%3A%2F%2Fzer0day.ch%3A1337&amp;tr=udp%3A%2F%2Fopen.demonii.com%3A1337&amp;tr=udp%3A%2F%2Ftracker.coppersurfer.tk%3A6969&amp;tr=udp%3A%2F%2Fexodus.desync.com%3A6969","seeders":0,"leechers":0,"uploader":"ElitePorn","files":1,"time":1443796593,"description":"Myfirstsexteacher Jewels Jade - Chad White HD 1080p\r\n~~~~~~~~~~~~~~~~~~~~~~~~~~~~~~~~~~~~~~~~~~~~~~~~~~~\r\n\r\nScreenshots:\r\n~~~~~~~~~~~~ \nhttp://picturescream.asia/soft/kqU\r\n \nhttp://picturescream.asia/soft/kqb\r\n \nhttp://picturescream.asia/soft/kqk\r\n \nhttp://picturescream.asia/soft/kqs\r\n \nhttp://picturescream.asia/soft/kq8\r\n \nhttp://picturescream.asia/soft/kqG\r\n\r\n\r\nVideos Info:\r\n~~~~~~~~~~~~\r\nSize: 2.78 GB\r\nDuration: 32:05 \t\r\nResolution: 1920x1080","torrent":{"xt":"urn:btih:aaa2a67e10b85d5c7927e456c4ae55bbbf44e7b6","amp;dn":"Myfirstsexteacher+Jewels+Jade+-+Chad+White+HD+1080p","amp;tr":["udp%3A%2F%2Ftracker.leechers-paradise.org%3A6969","udp%3A%2F%2Fzer0day.ch%3A1337","udp%3A%2F%2Fopen.demonii.com%3A1337","udp%3A%2F%2Ftracker.coppersurfer.tk%3A6969","udp%3A%2F%2Fexodus.desync.com%3A6969"],"infoHash":"aaa2a67e10b85d5c7927e456c4ae55bbbf44e7b6","infoHashBuffer":{"type":"Buffer","data":[170,162,166,126,16,184,93,92,121,39,228,86,196,174,85,187,191,68,231,182]},"announce":[],"urlList":[]}}