{"title":"Rock.N.Roll.In.My.Butthole.5.XXX.DVDRip.x264-CiCXXX","uid":12507715,"size":2164340270,"categoryP":"porn","categoryS":"movies","magnet":"?xt=urn:btih:ae17d6e4a0edb889da4a00f1f73cffd4f556f938&amp;dn=Rock.N.Roll.In.My.Butthole.5.XXX.DVDRip.x264-CiCXXX&amp;tr=udp%3A%2F%2Ftracker.leechers-paradise.org%3A6969&amp;tr=udp%3A%2F%2Fzer0day.ch%3A1337&amp;tr=udp%3A%2F%2Fopen.demonii.com%3A1337&amp;tr=udp%3A%2F%2Ftracker.coppersurfer.tk%3A6969&amp;tr=udp%3A%2F%2Fexodus.desync.com%3A6969","seeders":0,"leechers":1,"uploader":"0-DayXXX","files":1,"time":1443476976,"description":"---------------------------------------\nRock.N.Roll.In.My.Butthole.5.XXX.DVDRip.x264-CiCXXX\n---------------------------------------\nScreenshot(s): \nhttp://imgsay.com/?v=560494.jpg\n\n---------------------------------------\nFormat:\t\tMPEG-4\nSize:\t\t2.02 GiB\nDuration:\t2h 37min\nResolution:\t720x404\nBitrate:\t1706Kbps\n---------------------------------------\nIf you like this torrent, please post a comment!\n\nDon't forget to seed!","torrent":{"xt":"urn:btih:ae17d6e4a0edb889da4a00f1f73cffd4f556f938","amp;dn":"Rock.N.Roll.In.My.Butthole.5.XXX.DVDRip.x264-CiCXXX","amp;tr":["udp%3A%2F%2Ftracker.leechers-paradise.org%3A6969","udp%3A%2F%2Fzer0day.ch%3A1337","udp%3A%2F%2Fopen.demonii.com%3A1337","udp%3A%2F%2Ftracker.coppersurfer.tk%3A6969","udp%3A%2F%2Fexodus.desync.com%3A6969"],"infoHash":"ae17d6e4a0edb889da4a00f1f73cffd4f556f938","infoHashBuffer":{"type":"Buffer","data":[174,23,214,228,160,237,184,137,218,74,0,241,247,60,255,212,245,86,249,56]},"announce":[],"urlList":[]}}