{"title":"Dragon Con EFForums 2015 - MP3","uid":12529017,"size":1851852662,"categoryP":"audio","categoryS":"audio_books","magnet":"?xt=urn:btih:bda0c035ed002430fd1e4f1db53576705d4906fc&amp;dn=Dragon+Con+EFForums+2015+-+MP3&amp;tr=udp%3A%2F%2Ftracker.leechers-paradise.org%3A6969&amp;tr=udp%3A%2F%2Fzer0day.ch%3A1337&amp;tr=udp%3A%2F%2Fopen.demonii.com%3A1337&amp;tr=udp%3A%2F%2Ftracker.coppersurfer.tk%3A6969&amp;tr=udp%3A%2F%2Fexodus.desync.com%3A6969","seeders":0,"leechers":0,"uploader":"ktetch","files":31,"time":1444203653,"description":"Audio from the 2015 Electronic Frontier Forums track at Dragon*Con.\r\n\r\n33+ Hours of audio covering everything from the Edward Snowden and the NSA, Ingress, and PGP, through cryptography (specifically CIA's Kryptos) and how to file Freedom of Information Requests and Copyright Trolls, to 'What To Do If Police Want To Search Your Electronic Device', and 10 rules for dealing with police encounters\r\n\r\nAlso includes the annual favourite, Hacking 101\r\n\r\nMore details, including a full program list is at http://eff.dragoncon.org/2015-schedule/\r\n\r\n-\r\nMP3 format (OGG format available in another torrent)\r\nAudio released under a CC-BY-NC-SA license","torrent":{"xt":"urn:btih:bda0c035ed002430fd1e4f1db53576705d4906fc","amp;dn":"Dragon+Con+EFForums+2015+-+MP3","amp;tr":["udp%3A%2F%2Ftracker.leechers-paradise.org%3A6969","udp%3A%2F%2Fzer0day.ch%3A1337","udp%3A%2F%2Fopen.demonii.com%3A1337","udp%3A%2F%2Ftracker.coppersurfer.tk%3A6969","udp%3A%2F%2Fexodus.desync.com%3A6969"],"infoHash":"bda0c035ed002430fd1e4f1db53576705d4906fc","infoHashBuffer":{"type":"Buffer","data":[189,160,192,53,237,0,36,48,253,30,79,29,181,53,118,112,93,73,6,252]},"announce":[],"urlList":[]}}