{"title":"LETHAL HARDCORE-Daisy Monroe-Big Bodacious Knockers 12-New Relea","uid":12563604,"size":271955167,"categoryP":"porn","categoryS":"movie_clips","magnet":"?xt=urn:btih:c63e9de01c5ba6e57014e8fca6519073d6f62ffa&amp;dn=LETHAL+HARDCORE-Daisy+Monroe-Big+Bodacious+Knockers+12-New+Relea&amp;tr=udp%3A%2F%2Ftracker.leechers-paradise.org%3A6969&amp;tr=udp%3A%2F%2Fzer0day.ch%3A1337&amp;tr=udp%3A%2F%2Fopen.demonii.com%3A1337&amp;tr=udp%3A%2F%2Ftracker.coppersurfer.tk%3A6969&amp;tr=udp%3A%2F%2Fexodus.desync.com%3A6969","seeders":0,"leechers":0,"uploader":"Piratepr0n","files":1,"time":1444750175,"description":"-------------------------------------------------------------------------------------\nName:\nLETHAL HARDCORE-Daisy Monroe-Big Bodacious Knockers 12-New ReleaseOctober 13, 2015 torrentNew Release.mp4\n-------------------------------------------------------------------------------------\nFile list:\nLETHAL HARDCORE-Daisy Monroe-Big Bodacious Knockers 12-New ReleaseOctober 13, 2015 torrentNew Release.mp4 (259 MiB | 854x480 | 29min 27s | MPEG-4) \nhttp://imgfapper.com/img-561d085f7f1e8.html","torrent":{"xt":"urn:btih:c63e9de01c5ba6e57014e8fca6519073d6f62ffa","amp;dn":"LETHAL+HARDCORE-Daisy+Monroe-Big+Bodacious+Knockers+12-New+Relea","amp;tr":["udp%3A%2F%2Ftracker.leechers-paradise.org%3A6969","udp%3A%2F%2Fzer0day.ch%3A1337","udp%3A%2F%2Fopen.demonii.com%3A1337","udp%3A%2F%2Ftracker.coppersurfer.tk%3A6969","udp%3A%2F%2Fexodus.desync.com%3A6969"],"infoHash":"c63e9de01c5ba6e57014e8fca6519073d6f62ffa","infoHashBuffer":{"type":"Buffer","data":[198,62,157,224,28,91,166,229,112,20,232,252,166,81,144,115,214,246,47,250]},"announce":[],"urlList":[]}}