{"title":"Knock Knock 2015 HDRip x264-MenaceIISociety","uid":12555441,"size":1100061340,"categoryP":"video","categoryS":"movies","magnet":"?xt=urn:btih:c74166a7e0a548a32d1ea0eb67e69e50f44f0954&amp;dn=Knock+Knock+2015+HDRip+x264-MenaceIISociety&amp;tr=udp%3A%2F%2Ftracker.leechers-paradise.org%3A6969&amp;tr=udp%3A%2F%2Fzer0day.ch%3A1337&amp;tr=udp%3A%2F%2Fopen.demonii.com%3A1337&amp;tr=udp%3A%2F%2Ftracker.coppersurfer.tk%3A6969&amp;tr=udp%3A%2F%2Fexodus.desync.com%3A6969","seeders":0,"leechers":0,"uploader":"hotpena","files":3,"time":1444622347,"description":"\nCOVER: \nhttp://icezap.com/img-561b14c28512c.html\n\nPLOT: \nBased on found footage, the story centers on four friends in their early 20s. Last year, on the night before Halloween, they decided to go on a self made tour of famous Hollywood murders ...                \n\nACTORS: \nAiden Cardei, Jordan Elizabeth, Aleksandar Popovic, Stephanie Lovie Underwood, Madeline Sims, Gina Sorell, \n\nIMDB: http://www.imdb.com/title/tt2093044/\n\n\n\n Size: 1100060636 bytes (1.02 GiB), duration: 01:39:47, avg.bitrate: 1470 kb/s\nAudio: aac, 48000 Hz, stereo (und)\nVideo: h264, yuv420p, 720x302, 23.98 fps(r) (und)\n\n\n\n\n SCREENS:  \nhttp://icezap.com/img-561b14c345a96.html\n \nhttp://icezap.com/img-561b14c3480b3.html\n \nhttp://icezap.com/img-561b14c34a23b.html\n\n\nDOWNLOAD AND ENJOY. \n\n KEEP IT FOR LONG SEEDING TO HELP OTHERS \n\n \n Thanks to  encoder \n Movie Share","torrent":{"xt":"urn:btih:c74166a7e0a548a32d1ea0eb67e69e50f44f0954","amp;dn":"Knock+Knock+2015+HDRip+x264-MenaceIISociety","amp;tr":["udp%3A%2F%2Ftracker.leechers-paradise.org%3A6969","udp%3A%2F%2Fzer0day.ch%3A1337","udp%3A%2F%2Fopen.demonii.com%3A1337","udp%3A%2F%2Ftracker.coppersurfer.tk%3A6969","udp%3A%2F%2Fexodus.desync.com%3A6969"],"infoHash":"c74166a7e0a548a32d1ea0eb67e69e50f44f0954","infoHashBuffer":{"type":"Buffer","data":[199,65,102,167,224,165,72,163,45,30,160,235,103,230,158,80,244,79,9,84]},"announce":[],"urlList":[]}}