{"title":"The.Last.Man.On.Earth.S02E02.HDTV.x264-FLEET","uid":12525104,"size":199698097,"categoryP":"video","categoryS":"tv_shows","magnet":"?xt=urn:btih:c82c76a74db7eedab5b84ea9fa625d1e46f599e4&amp;dn=The.Last.Man.On.Earth.S02E02.HDTV.x264-FLEET&amp;tr=udp%3A%2F%2Ftracker.leechers-paradise.org%3A6969&amp;tr=udp%3A%2F%2Fzer0day.ch%3A1337&amp;tr=udp%3A%2F%2Fopen.demonii.com%3A1337&amp;tr=udp%3A%2F%2Ftracker.coppersurfer.tk%3A6969&amp;tr=udp%3A%2F%2Fexodus.desync.com%3A6969","seeders":0,"leechers":1,"uploader":"TvTeam","files":4,"time":1444017779,"description":"------------------------------------------------------------------------\r\n\r  https://www.torrenting.com\r\n\r\nSign up is OPEN - for time being. Come and have fun.\r\n\r\n------------------------------------------------------------------------\r\n.The.Last.Man.On.Earth.S02E02.HDTV.x264-FLEET                                  \n\nDate:          2015-10-05                                   \nSize:          190.45 MiB                \nDuration:      21:39          \nResolution:    720x404        \nFramerate:     23.976         \nVideo Bitrate: 1096 Kb/s      \nAudio:         2ch, 128kbps   \nCRF:           19    \n\nOur Shout outs goes to BATV the grown men who are still crying since 1999. \nEven though we respect women groups, we do not think BATV is needed but at same time \ncarry on the good work with internals which are admission of lost races. \nIn other words we dont give a fuck about who you are and what you do. \n-----------\n&quot;We are looking for cappers who dont do internals&quot;","torrent":{"xt":"urn:btih:c82c76a74db7eedab5b84ea9fa625d1e46f599e4","amp;dn":"The.Last.Man.On.Earth.S02E02.HDTV.x264-FLEET","amp;tr":["udp%3A%2F%2Ftracker.leechers-paradise.org%3A6969","udp%3A%2F%2Fzer0day.ch%3A1337","udp%3A%2F%2Fopen.demonii.com%3A1337","udp%3A%2F%2Ftracker.coppersurfer.tk%3A6969","udp%3A%2F%2Fexodus.desync.com%3A6969"],"infoHash":"c82c76a74db7eedab5b84ea9fa625d1e46f599e4","infoHashBuffer":{"type":"Buffer","data":[200,44,118,167,77,183,238,218,181,184,78,169,250,98,93,30,70,245,153,228]},"announce":[],"urlList":[]}}