{"title":".The.Country.S14E70.HDTV.x264-DOCERE","uid":12326868,"size":271347599,"categoryP":"video","categoryS":"tv_shows","magnet":"?xt=urn:btih:d0d4a5ace8bce7b5fe63787585863995b1aa86ad&amp;dn=.The.Country.S14E70.HDTV.x264-DOCERE&amp;tr=udp%3A%2F%2Ftracker.openbittorrent.com%3A80&amp;tr=udp%3A%2F%2Fopen.demonii.com%3A1337&amp;tr=udp%3A%2F%2Ftracker.coppersurfer.tk%3A6969&amp;tr=udp%3A%2F%2Fexodus.desync.com%3A6969","seeders":0,"leechers":0,"uploader":"TvTeam","files":4,"time":1441126726,"description":"------------------------------------------------------------------------\n\n &lt;a href=&quot; https://www.torrenting.com&quot; rel=&quot;nofollow&quot; target=&quot;_NEW&quot;&gt; https://www.torrenting.com&lt;/a&gt;\n\nSign up is OPEN - for time being. Come and have fun.\n \n        Title.......: Escape To The Country\n         Episode.....: S14E70\n            Airdate.....: --13\n                Rel. Date...: 01-09-15\n                Language....: English\n                Runtime.....: 43mn 17s\n                Size........: 259MB\n                Resolution..: 720x404 / 16:9\n                Framerate...: 25\n                Video Format: AVC @ 706 Kbit crf 22 /slow\n                 Audio Format: AAC @ 125 Kbit\n               Source......: DVB Multicast\n                                                       \n          greetings goes out to our friends -          \n                               you know who you are!","torrent":{"xt":"urn:btih:d0d4a5ace8bce7b5fe63787585863995b1aa86ad","amp;dn":".The.Country.S14E70.HDTV.x264-DOCERE","amp;tr":["udp%3A%2F%2Ftracker.openbittorrent.com%3A80","udp%3A%2F%2Fopen.demonii.com%3A1337","udp%3A%2F%2Ftracker.coppersurfer.tk%3A6969","udp%3A%2F%2Fexodus.desync.com%3A6969"],"infoHash":"d0d4a5ace8bce7b5fe63787585863995b1aa86ad","infoHashBuffer":{"type":"Buffer","data":[208,212,165,172,232,188,231,181,254,99,120,117,133,134,57,149,177,170,134,173]},"announce":[],"urlList":[]}}