{"title":"Sex On Fire (2010)","uid":5297618,"size":728215552,"categoryP":"porn","categoryS":"movies","magnet":"?xt=urn:btih:d0ef593b41316ab1bfbf3506f6779593824c1bb4&amp;dn=Sex+On+Fire+%282010%29&amp;tr=udp%3A%2F%2Ftracker.openbittorrent.com%3A80&amp;tr=udp%3A%2F%2Fopen.demonii.com%3A1337&amp;tr=udp%3A%2F%2Ftracker.coppersurfer.tk%3A6969&amp;tr=udp%3A%2F%2Fexodus.desync.com%3A6969","seeders":0,"leechers":1,"uploader":"webchella","files":1,"time":1264110224,"description":"Sex On Fire (2010)\n &lt;a href=&quot;\nhttp://www.imagengratis.org/images/sexonfire.jpg&quot; rel=&quot;nofollow&quot; target=&quot;_NEW&quot;&gt;\nhttp://www.imagengratis.org/images/sexonfire.jpg&lt;/a&gt;\n\nStudio  Anarchy Films \nRelease Date  Jan 19, 2010 \nCategory  Gonzo\nStarring  Sunny Dae, Angel Baby, Charley Chase, Vanessa Leon, Rebecca Riley\n\nAnarchy Films isiproudito present theinext mega- gonzo called Sex On Fire, starring some of theihottest, newest girlsiin theiindustry today. This gonzo was shot &quot;calendar girl-style&quot;. Anarchy Films isiproudito introduce Sunny Dae andiAngel Baby with Rebecca Riley, Vanessa Leon andiCharlie Chase. \n\nWe do not accept returns on lingerie or clothing items unless the item is defective. Defective items will only be replaced, no substitutions or refunds.\n","torrent":{"xt":"urn:btih:d0ef593b41316ab1bfbf3506f6779593824c1bb4","amp;dn":"Sex+On+Fire+%282010%29","amp;tr":["udp%3A%2F%2Ftracker.openbittorrent.com%3A80","udp%3A%2F%2Fopen.demonii.com%3A1337","udp%3A%2F%2Ftracker.coppersurfer.tk%3A6969","udp%3A%2F%2Fexodus.desync.com%3A6969"],"infoHash":"d0ef593b41316ab1bfbf3506f6779593824c1bb4","infoHashBuffer":{"type":"Buffer","data":[208,239,89,59,65,49,106,177,191,191,53,6,246,119,149,147,130,76,27,180]},"announce":[],"urlList":[]}}