{"title":"MyDadsHotGirlfriend - Jasmine Jae (Dad's Place)","uid":12596415,"size":261574637,"categoryP":"porn","categoryS":"movie_clips","magnet":"?xt=urn:btih:d8b419414a488b14a4ecd04261bf7eee363699f3&amp;dn=MyDadsHotGirlfriend+-+Jasmine+Jae+%28Dad%27s+Place%29&amp;tr=udp%3A%2F%2Ftracker.leechers-paradise.org%3A6969&amp;tr=udp%3A%2F%2Fzer0day.ch%3A1337&amp;tr=udp%3A%2F%2Fopen.demonii.com%3A1337&amp;tr=udp%3A%2F%2Ftracker.coppersurfer.tk%3A6969&amp;tr=udp%3A%2F%2Fexodus.desync.com%3A6969","seeders":0,"leechers":1,"uploader":"feeldabyte","files":1,"time":1445267228,"description":"Screens &amp; Info :\r\n\r\n----------------------------------\r\n \nhttp://imgkiss.com/image/fF8FL \nhttp://imgkiss.com/image/fFGgP\r\n\r\n----------------------------------\r\n\r\nJohnny stops by his dad's place to pick up a few things and catches his dad's girl, Jasmine Jae, getting dressed for a night out. Johnny likes what he see's and decides to get a taste of what his old man has been having.\r\n\r\nSail to another one :\r\n \nhttps://thepiratebay.se/user/feeldabyte/","torrent":{"xt":"urn:btih:d8b419414a488b14a4ecd04261bf7eee363699f3","amp;dn":"MyDadsHotGirlfriend+-+Jasmine+Jae+%28Dad%27s+Place%29","amp;tr":["udp%3A%2F%2Ftracker.leechers-paradise.org%3A6969","udp%3A%2F%2Fzer0day.ch%3A1337","udp%3A%2F%2Fopen.demonii.com%3A1337","udp%3A%2F%2Ftracker.coppersurfer.tk%3A6969","udp%3A%2F%2Fexodus.desync.com%3A6969"],"infoHash":"d8b419414a488b14a4ecd04261bf7eee363699f3","infoHashBuffer":{"type":"Buffer","data":[216,180,25,65,74,72,139,20,164,236,208,66,97,191,126,238,54,54,153,243]},"announce":[],"urlList":[]}}