{"title":"[Passion-HD] Kendall Kayden (Magic Fingers - 25.09.15)","uid":12491201,"size":294234541,"categoryP":"porn","categoryS":"movie_clips","magnet":"?xt=urn:btih:e30113506aed517ee514aa20fca9685025423741&amp;dn=%5BPassion-HD%5D+Kendall+Kayden+%28Magic+Fingers+-+25.09.15%29&amp;tr=udp%3A%2F%2Ftracker.leechers-paradise.org%3A6969&amp;tr=udp%3A%2F%2Fzer0day.ch%3A1337&amp;tr=udp%3A%2F%2Fopen.demonii.com%3A1337&amp;tr=udp%3A%2F%2Ftracker.coppersurfer.tk%3A6969&amp;tr=udp%3A%2F%2Fexodus.desync.com%3A6969","seeders":0,"leechers":0,"uploader":"KayWily","files":1,"time":1443180898,"description":"[Passion-HD] Kendall Kayden (Magic Fingers - 25.09.15)\r\n\r\n \nhttp://porn-harbor.com/image/yI","torrent":{"xt":"urn:btih:e30113506aed517ee514aa20fca9685025423741","amp;dn":"%5BPassion-HD%5D+Kendall+Kayden+%28Magic+Fingers+-+25.09.15%29","amp;tr":["udp%3A%2F%2Ftracker.leechers-paradise.org%3A6969","udp%3A%2F%2Fzer0day.ch%3A1337","udp%3A%2F%2Fopen.demonii.com%3A1337","udp%3A%2F%2Ftracker.coppersurfer.tk%3A6969","udp%3A%2F%2Fexodus.desync.com%3A6969"],"infoHash":"e30113506aed517ee514aa20fca9685025423741","infoHashBuffer":{"type":"Buffer","data":[227,1,19,80,106,237,81,126,229,20,170,32,252,169,104,80,37,66,55,65]},"announce":[],"urlList":[]}}