{"title":"She's So Small 3 - FoxyDi","uid":12346391,"size":1180255314,"categoryP":"porn","categoryS":"movies","magnet":"?xt=urn:btih:ed4a330cdde706bdbe700c8dc766747171f5b942&amp;dn=She%27s+So+Small+3+-+FoxyDi&amp;tr=udp%3A%2F%2Ftracker.openbittorrent.com%3A80&amp;tr=udp%3A%2F%2Fopen.demonii.com%3A1337&amp;tr=udp%3A%2F%2Ftracker.coppersurfer.tk%3A6969&amp;tr=udp%3A%2F%2Fexodus.desync.com%3A6969","seeders":0,"leechers":0,"uploader":"irealu69","files":1,"time":1441362431,"description":"She's So Small 3 - FoxyDi\n~~~~~~~~~~~~~~~~~~~~~~~~~~~~~~~~~~\n\nSynopsis: Foxy Di - Imagine her looking up at you!JAde Jantzen - Little ones love playing with balls!Ava Mendes - Fill her pussy and she'll take care of her ass!Kacy Lane - Teeny tiny titties!Sierra Navadah - Piledrive that tiny pussy!\n\nCast: Foxy Di, Jade Jantzen, Kacy Lane, Sierra Nevadah, Ava Mendes\n\nScreenshots:\n~~~~~~~~~~~~ &lt;a href=&quot;\nhttp://www.picturescream.com/x/clean/GvLw&quot; rel=&quot;nofollow&quot; target=&quot;_NEW&quot;&gt;\nhttp://www.picturescream.com/x/clean/GvLw&lt;/a&gt;\n &lt;a href=&quot;\nhttp://www.picturescream.com/x/clean/GvgN&quot; rel=&quot;nofollow&quot; target=&quot;_NEW&quot;&gt;\nhttp://www.picturescream.com/x/clean/GvgN&lt;/a&gt;\n &lt;a href=&quot;\nhttp://www.picturescream.com/x/clean/Gvgf&quot; rel=&quot;nofollow&quot; target=&quot;_NEW&quot;&gt;\nhttp://www.picturescream.com/x/clean/Gvgf&lt;/a&gt;\n &lt;a href=&quot;\nhttp://www.picturescream.com/x/clean/Gvgq&quot; rel=&quot;nofollow&quot; target=&quot;_NEW&quot;&gt;\nhttp://www.picturescream.com/x/clean/Gvgq&lt;/a&gt;\n &lt;a href=&quot;\nhttp://www.picturescream.com/x/clean/GvgG&quot; rel=&quot;nofollow&quot; target=&quot;_NEW&quot;&gt;\nhttp://www.picturescream.com/x/clean/GvgG&lt;/a&gt;\n &lt;a href=&quot;\nhttp://www.picturescream.com/x/clean/GvgJ&quot; rel=&quot;nofollow&quot; target=&quot;_NEW&quot;&gt;\nhttp://www.picturescream.com/x/clean/GvgJ&lt;/a&gt;\n\nVideos Info:\n~~~~~~~~~~~~\nSize: 1.099 GB\nDuration: 2 hrs. 22 mins. \t\nResolution: 720x400","torrent":{"xt":"urn:btih:ed4a330cdde706bdbe700c8dc766747171f5b942","amp;dn":"She%27s+So+Small+3+-+FoxyDi","amp;tr":["udp%3A%2F%2Ftracker.openbittorrent.com%3A80","udp%3A%2F%2Fopen.demonii.com%3A1337","udp%3A%2F%2Ftracker.coppersurfer.tk%3A6969","udp%3A%2F%2Fexodus.desync.com%3A6969"],"infoHash":"ed4a330cdde706bdbe700c8dc766747171f5b942","infoHashBuffer":{"type":"Buffer","data":[237,74,51,12,221,231,6,189,190,112,12,141,199,102,116,113,113,245,185,66]},"announce":[],"urlList":[]}}