{"title":"Match.Of.The.Day.Two.2015.09.27.XviD-AFG","uid":12504760,"size":2293803865,"categoryP":"video","categoryS":"tv_shows","magnet":"?xt=urn:btih:f04d2c0596359c09ec9464bc5c060ec8a0fdd97a&amp;dn=Match.Of.The.Day.Two.2015.09.27.XviD-AFG&amp;tr=udp%3A%2F%2Ftracker.leechers-paradise.org%3A6969&amp;tr=udp%3A%2F%2Fzer0day.ch%3A1337&amp;tr=udp%3A%2F%2Fopen.demonii.com%3A1337&amp;tr=udp%3A%2F%2Ftracker.coppersurfer.tk%3A6969&amp;tr=udp%3A%2F%2Fexodus.desync.com%3A6969","seeders":0,"leechers":0,"uploader":"TvTeam","files":12,"time":1443436030,"description":"------------------------------------------------------------------------\r\n\r  https://www.torrenting.com\r\n\r\nSign up is OPEN - for time being. Come and have fun.\r\n\r\n------------------------------------------------------------------------\r\n.[Title] Match.Of.The.Day.Two.2015.09.27.XviD-AFG [/Title] \r\n\r\n[pre][b][color=red] Match.Of.The.Day.Two.2015.09.27.XviD-AFG.avi [/color][/b]\r\n\r\n Duration          : 00:49:06 \r\n Release size      : 2.13 GB \r\n Video Bitrate     : 6 076 Kbps \r\n Frame rate        : 50.000 Fps  \r\n MP3 2ch CBR       : 128 kbps \r\n Video resolution  : 640x360  (16:9) \r\n\r\n[","torrent":{"xt":"urn:btih:f04d2c0596359c09ec9464bc5c060ec8a0fdd97a","amp;dn":"Match.Of.The.Day.Two.2015.09.27.XviD-AFG","amp;tr":["udp%3A%2F%2Ftracker.leechers-paradise.org%3A6969","udp%3A%2F%2Fzer0day.ch%3A1337","udp%3A%2F%2Fopen.demonii.com%3A1337","udp%3A%2F%2Ftracker.coppersurfer.tk%3A6969","udp%3A%2F%2Fexodus.desync.com%3A6969"],"infoHash":"f04d2c0596359c09ec9464bc5c060ec8a0fdd97a","infoHashBuffer":{"type":"Buffer","data":[240,77,44,5,150,53,156,9,236,148,100,188,92,6,14,200,160,253,217,122]},"announce":[],"urlList":[]}}