{"title":"FemdomEmpire - Ball Chariot of Pain 1080p","uid":12527397,"size":757043700,"categoryP":"porn","categoryS":"hd___movies","magnet":"?xt=urn:btih:fef19e06d7847c3e52ec60736b405ca129b002a2&amp;dn=FemdomEmpire+-+Ball+Chariot+of+Pain+1080p&amp;tr=udp%3A%2F%2Ftracker.leechers-paradise.org%3A6969&amp;tr=udp%3A%2F%2Fzer0day.ch%3A1337&amp;tr=udp%3A%2F%2Fopen.demonii.com%3A1337&amp;tr=udp%3A%2F%2Ftracker.coppersurfer.tk%3A6969&amp;tr=udp%3A%2F%2Fexodus.desync.com%3A6969","seeders":0,"leechers":0,"uploader":"merzedes","files":1,"time":1444153759,"description":"\nBall Chariot of Pain\r\n \r\nFeatured Models: Yasmin Scott\r\n\r\n\r\n1080p MP4.\r\n\r\n\r\nMistress Yasmin has deemed her slaves balls mostly useless. She decides that if he wants to keep his balls she will have to find practical use for them. Yasmin straps them to her chariot and makes him pull her around the dungeon, what a fun and humiliating method of transportation. She mercilessly slaps his ass hard with her riding crop leaving red welts on his ass as a signal to pull faster, she laughs as muffled screams come from his head box. \r\n\r\nScreens \nhttp://s24.postimg.org/epggit8lx/feballchariot.jpg\r\n\r\nUploaded by Merzedes and Shallow2\r\n\r\n19 000 Femdom/BDSM/Fetish torrentuploads completed. Man.. feels like every 1000 goes by faster and faster ;)\r\n\r\nJust keep on leaving us the nice comments below and we are happy :)\r\n\r\nAny Questions ?? Read our FAQ!!\r\n \nhttps://yuq.me/users/23/079/W2kwa6hEeP.png\r\n \nhttp://s16.postimg.org/rxyfmji7p/Merzedes_Shallow2_FAQ_The_Pirate_Bay.jpg\r\n\r\nCheers :-)","torrent":{"xt":"urn:btih:fef19e06d7847c3e52ec60736b405ca129b002a2","amp;dn":"FemdomEmpire+-+Ball+Chariot+of+Pain+1080p","amp;tr":["udp%3A%2F%2Ftracker.leechers-paradise.org%3A6969","udp%3A%2F%2Fzer0day.ch%3A1337","udp%3A%2F%2Fopen.demonii.com%3A1337","udp%3A%2F%2Ftracker.coppersurfer.tk%3A6969","udp%3A%2F%2Fexodus.desync.com%3A6969"],"infoHash":"fef19e06d7847c3e52ec60736b405ca129b002a2","infoHashBuffer":{"type":"Buffer","data":[254,241,158,6,215,132,124,62,82,236,96,115,107,64,92,161,41,176,2,162]},"announce":[],"urlList":[]}}